ens160/__init__.py
ens160/commands.py
ens160/driver.py
ens160/i2c.py
ens160/icommunication.py
ens160/mock.py
ens160/op_modes.py
ens160/registers.py
ens160/status.py
ens160-0.0.2.dist-info/METADATA
ens160-0.0.2.dist-info/WHEEL
ens160-0.0.2.dist-info/licenses/LICENSE
ens160-0.0.2.dist-info/RECORD
