Metadata-Version: 2.3
Name: ens160
Version: 0.0.2
Summary: ENS160 Air Quality Sensor driver
Project-URL: Homepage, https://github.com/altera2015/ENS160
Project-URL: Issues, https://github.com/altera2015/ENS160/issues
Author-email: Ron Bessems <rbessems@gmail.com>
License-File: LICENSE
Classifier: License :: OSI Approved :: MIT License
Classifier: Operating System :: OS Independent
Classifier: Programming Language :: Python :: 3
Requires-Python: >=3.10
